{
  "type": "book",
  "events": [],
  "previousSourceRefs": [],
  "id": "9782357780323",
  "title": "Enlèvements extraterrestres et rencontres rapprochées",
  "authors": [
    "Ludovic Chapier"
  ],
  "subTitle": "le point sur 50 ans d'études à travers des cas récents",
  "series": "",
  "publication": {
    "time": "2011",
    "publisher": "Interkeltia"
  },
  "dirName": "time/2/0/1/1/LudovicChapier_EnlevementsExtraterrestresEtRencontresRapprochees_Interkeltia",
  "summary": "Ce livre présente des cas réels et récents (2010, 2011) de rencontres rapprochées aux Etats-Unis. Le phénomène des abductions est étudié depuis 50 ans et de nombreux éléments relatifs à la réalité du phénomène sont désormais absolument certains. Un chapitre est consacré aux conclusions actuelles des chercheurs les plus en pointe, de Budd Hopkins (décédé durant l'été 2011) à David Jacobs notamment. Ce livre répond aussi à de nombreuses questions connexes liées aux abductions, qu'il s'agisse de traces physiques sur les victimes ou de la question des bases extraterrestres sur Terre. L'affaire du Brooklyn Bridge de 1989 est longuement évoquée ainsi que d'autres cas moins connus du grand public car issus de livres n'ayant pas été traduits en français. Le lecteur trouvera de nombreux liens vers les sites web des chercheurs cités, ainsi que vers des vidéos en ligne. Ce livre constitue un ouvrage de synthèse qui donne une vue d'ensemble du phénomène des enlèvements, tout en s'appuyant sur des faits. La démarche de l'auteur se veut rationnelle et objective. Les faits contenus dans ce livre sont vérifiables...",
  "variants": []
}